README.md
setup.py
eqhl/__init__.py
eqhl.egg-info/PKG-INFO
eqhl.egg-info/SOURCES.txt
eqhl.egg-info/dependency_links.txt
eqhl.egg-info/not-zip-safe
eqhl.egg-info/top_level.txt