Metadata-Version: 1.0
Name: eqhl
Version: 0.2
Summary: A highlighting system to explain equations and their components easily
Home-page: https://gitlab.com/trajectory/eqhl
Author: Spencer Burris
Author-email: sburris@posteo.net
License: ISC
Platform: UNKNOWN
